HLAfreq/HLAfreq.py
HLAfreq/HLAfreq_pymc.py
HLAfreq/__init__.py
HLAfreq/examples.py
HLAfreq-0.0.5.dist-info/LICENSE
HLAfreq-0.0.5.dist-info/METADATA
HLAfreq-0.0.5.dist-info/WHEEL
HLAfreq-0.0.5.dist-info/top_level.txt
HLAfreq-0.0.5.dist-info/RECORD
