Metadata-Version: 2.1
Name: HLAfreq
Version: 0.0.5
Summary: Download and combine HLA frequency data from multiple studies
Home-page: https://github.com/BarinthusBio/HLAfreq
Author: David Wells
Author-email: david.wells@BarinthusBio.co.uk
Project-URL: Documentaion, https://barinthusbio.github.io/HLAfreq/HLAfreq.html
Project-URL: Tracker, https://github.com/BarinthusBio/HLAfreq/issues
Classifier: Programming Language :: Python :: 3
Classifier: Operating System :: OS Independent
Requires-Python: >=3.10
License-File: LICENSE
Requires-Dist: bs4
Requires-Dist: requests
Requires-Dist: pandas
Requires-Dist: numpy >=1.24.0
Requires-Dist: matplotlib >=3.6.0
Requires-Dist: scipy >=1.10.0
Requires-Dist: pymc >=3
Requires-Dist: arviz
